skinAPI.py
skin_APIv-1.1.dist-info/METADATA
skin_APIv-1.1.dist-info/WHEEL
skin_APIv-1.1.dist-info/top_level.txt
skin_APIv-1.1.dist-info/RECORD
