Metadata-Version: 2.1
Name: skin-APIv
Version: 1.1
Summary: The API for melanoma image skin level prediction.
Home-page: UNKNOWN
Author: Claire
Author-email: UNKNOWN
License: LGPL
Platform: UNKNOWN
